fifo.v
module fifo (
    input  wire        clk,
    input  wire        rst,
    input  wire        wr_en,
    input  wire        rd_en,
    input  wire [7:0]  buf_in,

    output reg  [7:0]  buf_out,
    output wire        buf_empty,
    output wire        buf_full,
    output reg  [6:0]  fifo_counter
);

    // FIFO memory (64 x 8)
    reg [7:0] buf_mem [0:63];

    // Read & Write pointers
    reg [5:0] rd_ptr;
    reg [5:0] wr_ptr;

    // Empty & Full flags
    assign buf_empty = (fifo_counter == 0);
    assign buf_full  = (fifo_counter == 64);

    // -------------------------
    // WRITE OPERATION
    // -------------------------
    always @(posedge clk or posedge rst) begin
        if (rst) begin
            wr_ptr <= 0;
        end else if (wr_en && !buf_full) begin
            buf_mem[wr_ptr] <= buf_in;
            wr_ptr <= wr_ptr + 1;
        end
    end

    // -------------------------
    // READ OPERATION
    // -------------------------
    always @(posedge clk or posedge rst) begin
        if (rst) begin
            rd_ptr  <= 0;
            buf_out <= 0;
        end else if (rd_en && !buf_empty) begin
            buf_out <= buf_mem[rd_ptr];
            rd_ptr  <= rd_ptr + 1;
        end
    end

    // -------------------------
    // FIFO COUNTER
    // -------------------------
    always @(posedge clk or posedge rst) begin
        if (rst) begin
            fifo_counter <= 0;
        end else begin
            case ({wr_en && !buf_full, rd_en && !buf_empty})
                2'b10: fifo_counter <= fifo_counter + 1; // write only
                2'b01: fifo_counter <= fifo_counter - 1; // read only
                default: fifo_counter <= fifo_counter;   // both or none
            endcase
        end
    end

endmodule

fifo_tb.v
`include "fifo.v"

module fifo_tb;

    reg clk;
    reg rst;
    reg wr_en;
    reg rd_en;
    reg [7:0] buf_in;

    wire [7:0] buf_out;
    wire buf_empty;
    wire buf_full;
    wire [6:0] fifo_counter;

    // DUT instantiation
    fifo dut (
        .clk(clk),
        .rst(rst),
        .buf_in(buf_in),
        .buf_out(buf_out),
        .wr_en(wr_en),
        .rd_en(rd_en),
        .buf_empty(buf_empty),
        .buf_full(buf_full),
        .fifo_counter(fifo_counter)
    );

    // Clock generation (10ns period)
    always #5 clk = ~clk;

    
    initial begin
        // Initial values
        clk = 0;
        rst = 1;
        wr_en = 0;
        rd_en = 0;
        buf_in = 0;

        // Reset
        #10 rst = 0;

        // WRITE 3 values into FIFO
        @(posedge clk);
        wr_en = 1; buf_in = 8'h11;

        @(posedge clk);
        buf_in = 8'h22;

        @(posedge clk);
        buf_in = 8'h33;

        @(posedge clk);
        wr_en = 0;

        // READ 3 values from FIFO
        @(posedge clk);
        rd_en = 1;

        @(posedge clk);
        @(posedge clk);
        @(posedge clk);

        rd_en = 0;

        // Simultaneous READ & WRITE
        @(posedge clk);
        wr_en = 1; rd_en = 1; buf_in = 8'h44;

        @(posedge clk);
        wr_en = 0; rd_en = 0;

        #20 $finish;
    end


    initial begin
        $monitor("TIME=%0t | wr=%b rd=%b in=%h out=%h | empty=%b full=%b count=%d",
                  $time, wr_en, rd_en, buf_in, buf_out,
                  buf_empty, buf_full, fifo_counter);
    end

    
    initial begin
        $dumpfile("fifo.vcd");
        $dumpvars(0, fifo_tb);
    end

endmodule

fifo.vcd
$date
	Wed Dec 31 11:39:09 2025
$end
$version
	Icarus Verilog
$end
$timescale
	1s
$end
$scope module fifo_tb $end
$var wire 1 ! buf_empty $end
$var wire 1 " buf_full $end
$var wire 8 # buf_out [7:0] $end
$var wire 7 $ fifo_counter [6:0] $end
$var reg 8 % buf_in [7:0] $end
$var reg 1 & clk $end
$var reg 1 ' rd_en $end
$var reg 1 ( rst $end
$var reg 1 ) wr_en $end
$scope module dut $end
$var wire 1 ! buf_empty $end
$var wire 1 " buf_full $end
$var wire 8 * buf_in [7:0] $end
$var wire 1 + clk $end
$var wire 1 , rd_en $end
$var wire 1 - rst $end
$var wire 1 . wr_en $end
$var reg 8 / buf_out [7:0] $end
$var reg 7 0 fifo_counter [6:0] $end
$var reg 6 1 rd_ptr [5:0] $end
$var reg 6 2 wr_ptr [5:0] $end
$upscope $end
$upscope $end
$enddefinitions $end
#0
$dumpvars
b0 2
b0 1
b0 0
b0 /
0.
1-
0,
0+
b0 *
0)
1(
0'
0&
b0 %
b0 $
b0 #
0"
1!
$end
#5
1&
1+
#10
0&
0+
0(
0-
#15
b1 2
b1 0
0!
b1 $
b10001 %
b10001 *
1)
1.
1&
1+
#20
0&
0+
#25
b10 0
b10 $
b10 2
b100010 %
b100010 *
1&
1+
#30
0&
0+
#35
b11 2
b11 0
b11 $
b110011 %
b110011 *
1&
1+
#40
0&
0+
#45
0)
0.
1&
1+
#50
0&
0+
#55
b1 1
b10001 /
b10001 #
b10 0
b10 $
1'
1,
1&
1+
#60
0&
0+
#65
b1 0
b1 $
b10 1
b100010 /
b100010 #
1&
1+
#70
0&
0+
#75
b11 1
b110011 /
b110011 #
b0 0
1!
b0 $
1&
1+
#80
0&
0+
#85
0'
0,
1&
1+
#90
0&
0+
#95
b100 2
b1 0
0!
b1 $
b1000100 %
b1000100 *
1'
1,
1)
1.
1&
1+
#100
0&
0+
#105
0'
0,
0)
0.
1&
1+
